comon_crawler/__init__.py
comon_crawler/core.py
comon_crawler/crawler.py
comon_crawler/schemas.py
comon_crawler-0.9.8.dist-info/WHEEL
comon_crawler-0.9.8.dist-info/METADATA
comon_crawler-0.9.8.dist-info/RECORD
