Metadata-Version: 2.1
Name: comon-crawler
Version: 0.9.8
Summary: 
Author: roci
Author-email: you@example.com
Requires-Python: >=3.8,<4.0
Classifier: Programming Language :: Python :: 3
Classifier: Programming Language :: Python :: 3.8
Classifier: Programming Language :: Python :: 3.9
Requires-Dist: pydantic (>=1.8.1,<2.0.0)
Requires-Dist: python-dotenv (>=0.17.0,<0.18.0)
Requires-Dist: selenium (>=3.141.0,<4.0.0)
